LICENSE
README.md
setup.cfg
setup.py
rick_mailer/__init__.py
rick_mailer/message.py
rick_mailer/utils.py
rick_mailer.egg-info/PKG-INFO
rick_mailer.egg-info/SOURCES.txt
rick_mailer.egg-info/dependency_links.txt
rick_mailer.egg-info/not-zip-safe
rick_mailer.egg-info/requires.txt
rick_mailer.egg-info/top_level.txt
rick_mailer/backends/__init__.py
rick_mailer/backends/base.py
rick_mailer/backends/console.py
rick_mailer/backends/locmem.py
rick_mailer/backends/smtp.py
tests/__init__.py
tests/common.py
tests/custombackend.py
tests/test_backends.py
tests/test_mailer.py