Metadata-Version: 2.1
Name: rick-mailer
Version: 1.0.2
Summary: Simple library to send emails
Home-page: https://git.oddbit.org/OddBit/rick-mailer
Author: João Pinheiro
License: BSD-3-Clause
Project-URL: Documentation, https://docs.oddbit.org/rick-mailer/
Project-URL: Source, https://git.oddbit.org/OddBit/rick-mailer
Classifier: Environment :: Web Environment
Classifier: Development Status :: 4 - Beta
Classifier: Intended Audience :: Developers
Classifier: License :: OSI Approved :: BSD License
Classifier: Operating System :: OS Independent
Classifier: Programming Language :: Python
Classifier: Programming Language :: Python :: 3.8
Classifier: Programming Language :: Python :: 3.9
Classifier: Programming Language :: Python :: 3.10
Classifier: Programming Language :: Python :: 3.11
Classifier: Topic :: Internet :: WWW/HTTP :: Dynamic Content
Classifier: Topic :: Software Development :: Libraries :: Python Modules
Requires-Python: >=3.8
License-File: LICENSE
